ostk/__init__.py
ostk/core/OpenSpaceToolkitCorePy.cpython-313-x86_64-linux-gnu.so
ostk/core/__init__.py
ostk/core/__init__.pyi
ostk/core/container.pyi
ostk/core/filesystem.pyi
ostk/core/libopen-space-toolkit-core.so.5
ostk/core/type.pyi
ostk/core/test/__init__.py
ostk/core/test/containers/__init__.py
ostk/core/test/containers/test_array.py
ostk/core/test/containers/test_dictionary.py
ostk/core/test/containers/test_object.py
ostk/core/test/filesystem/__init__.py
ostk/core/test/filesystem/test_directory.py
ostk/core/test/filesystem/test_file.py
ostk/core/test/filesystem/test_path.py
ostk/core/test/filesystem/test_permissionset.py
ostk/core/test/types_/__init__.py
ostk/core/test/types_/test_integer.py
ostk/core/test/types_/test_real.py
ostk/core/test/types_/test_sign.py
ostk/core/test/types_/test_string.py
open_space_toolkit_core-5.2.0.dist-info/METADATA
open_space_toolkit_core-5.2.0.dist-info/WHEEL
open_space_toolkit_core-5.2.0.dist-info/top_level.txt
open_space_toolkit_core-5.2.0.dist-info/zip-safe
open_space_toolkit_core-5.2.0.dist-info/RECORD
