Metadata-Version: 2.2
Name: open-space-toolkit-core
Version: 5.2.0
Summary: Fundamental types, container and utility.
Author: Open Space Collective
Author-email: contact@open-space-collective.org
License: Apache License 2.0
Keywords: open-space-collective,open-space-toolkit core
Classifier: Development Status :: 3 - Alpha
Classifier: Programming Language :: Python :: 3
Classifier: License :: OSI Approved :: Apache Software License
Classifier: Operating System :: POSIX :: Linux
